snapy/__init__.py
snapy/archive_pt.py
snapy/diag_intEng_to_temp.py
snapy/exchange.py
snapy/py.typed
snapy/simple_decomp2d.py
snapy/snapy.cpython-39-x86_64-linux-gnu.so
snapy/write_init.py
snapy/api/__init__.py
snapy/api/pd_combine.py
snapy/api/pd_inspect.py
snapy/lib/libsnap_release.so
snapy/snap/CMakeLists.txt
snapy/snap/add_arg.h
snapy/snap/snap.h
snapy/snap/bc/bc.hpp
snapy/snap/bc/bc_dispatch.cpp
snapy/snap/bc/bc_dispatch.cu
snapy/snap/bc/bc_dispatch.hpp
snapy/snap/bc/bc_func.cpp
snapy/snap/bc/bc_func.hpp
snapy/snap/bc/flip_zero_impl.h
snapy/snap/bc/internal_boundary.cpp
snapy/snap/bc/internal_boundary.hpp
snapy/snap/bc/rectify_solid.cpp
snapy/snap/coord/cartesian.cpp
snapy/snap/coord/coord_dispatch.cpp
snapy/snap/coord/coord_dispatch.cu
snapy/snap/coord/coord_dispatch.hpp
snapy/snap/coord/coord_utils.cpp
snapy/snap/coord/coord_utils.hpp
snapy/snap/coord/coord_utils_impl.h
snapy/snap/coord/coordgen.cpp
snapy/snap/coord/coordgen.hpp
snapy/snap/coord/coordinate.cpp
snapy/snap/coord/coordinate.hpp
snapy/snap/coord/cubed_sphere6.nb
snapy/snap/coord/cubed_sphere_utils.cpp
snapy/snap/coord/cubed_sphere_utils.hpp
snapy/snap/coord/cubed_sphere_utils_impl.h
snapy/snap/coord/cylindrical.cpp_
snapy/snap/coord/gnomonic_equiangle.cpp
snapy/snap/coord/gnomonic_equiangle.cpp_
snapy/snap/coord/gnomonic_equiangle.hpp
snapy/snap/coord/spherical_polar.cpp
snapy/snap/coord/spherical_polar.hpp
snapy/snap/coord/spherical_utils.cpp
snapy/snap/coord/spherical_utils.hpp
snapy/snap/diagnostics/CMakeLists.txt
snapy/snap/diagnostics/anomaly.cpp
snapy/snap/diagnostics/buoyancy.cpp
snapy/snap/diagnostics/curl.cpp
snapy/snap/diagnostics/diagnostics.cpp
snapy/snap/diagnostics/diagnostics.hpp
snapy/snap/diagnostics/diagnostics_factory.cpp
snapy/snap/diagnostics/divergence.cpp
snapy/snap/diagnostics/hydro_flux.cpp
snapy/snap/diagnostics/hydro_mean.cpp
snapy/snap/diagnostics/radiative_flux.cpp_
snapy/snap/diagnostics/v1_moments.cpp_
snapy-1.2.1.dist-info/METADATA
snapy-1.2.1.dist-info/WHEEL
snapy-1.2.1.dist-info/entry_points.txt
snapy-1.2.1.dist-info/top_level.txt
snapy-1.2.1.dist-info/RECORD
snapy-1.2.1.dist-info/licenses/LICENSE
snapy-1.2.1.dist-info/sboms/auditwheel.cdx.json
