Metadata-Version: 2.4
Name: snapy
Version: 1.2.1
Summary: Compressible Finite Volume Solver for Atmospheric Dynamics, Chemistry and Thermodynamics
Author-email: Cheng Li <chengcli@umich.edu>
License: LICENSE
Project-URL: Homepage, https://github.com/chengcli/snapy
Project-URL: Documentation, https://snapy.readthedocs.io
Classifier: Development Status :: 3 - Alpha
Classifier: Intended Audience :: Science/Research
Classifier: Natural Language :: English
Classifier: Programming Language :: C
Classifier: Programming Language :: C++
Classifier: Programming Language :: Python :: 3.9
Classifier: Programming Language :: Python :: 3.10
Classifier: Programming Language :: Python :: 3.11
Classifier: Programming Language :: Python :: Implementation :: CPython
Classifier: Topic :: Scientific/Engineering :: Atmospheric Science
Classifier: Topic :: Scientific/Engineering :: Physics
Classifier: Topic :: Scientific/Engineering :: Astronomy
Requires-Python: >=3.9
License-File: LICENSE
Requires-Dist: numpy
Requires-Dist: kintera>=1.2.6
Dynamic: license-file
